.travis.yml
AUTHORS.rst
CONTRIBUTING.rst
HISTORY.rst
LICENSE
MANIFEST.in
Makefile
README.rst
VERSION.txt
requirements.txt
runtests.py
setup.cfg
setup.py
tox.ini
docs/Makefile
docs/authors.rst
docs/conf.py
docs/contributing.rst
docs/history.rst
docs/index.rst
docs/installation.rst
docs/license.rst
docs/make.bat
docs/modules.rst
docs/pkgsetcomp.rst
docs/readme.rst
docs/usage.rst
pkgsetcomp/__init__.py
pkgsetcomp/pkgsetcomp.py
pkgsetcomp/pyrpo.py
pkgsetcomp.egg-info/PKG-INFO
pkgsetcomp.egg-info/SOURCES.txt
pkgsetcomp.egg-info/dependency_links.txt
pkgsetcomp.egg-info/entry_points.txt
pkgsetcomp.egg-info/not-zip-safe
pkgsetcomp.egg-info/top_level.txt
tests/__init__.py
tests/test_pkgsetcomp.py
tests/testdata/ubuntu-12.04.4-desktop-i386.manifest