Metadata-Version: 1.1
Name: pkgsetcomp
Version: 0.1.3
Summary: Compare packages listed in a debian/ubuntu APT .manifest with installed packages
Home-page: https://github.com/westurner/pkgsetcomp
Author: Wes Turner
Author-email: wes@wrd.nu
License: BSD
Download-URL: https://github.com/westurner/pkgsetcomp/releases
Keywords: pkgsetcomp apt deb debian ubuntu
Platform: UNKNOWN
Classifier: Development Status :: 2 - Pre-Alpha
Classifier: Intended Audience :: Developers
Classifier: License :: OSI Approved :: BSD License
Classifier: Natural Language :: English
Classifier: Programming Language :: Python :: 2
Classifier: Programming Language :: Python :: 2.7
